{
  "query": "검색엔진최적화",
  "language": "ko",
  "num_results": 40,
  "topics": [
    {
      "id": 0,
      "keywords": [
        "검색",
        "엔진",
        "최적화",
        "콘텐츠",
        "사이트",
        "페이지",
        "구글",
        "웹사이트",
        "결과",
        "네이버"
      ],
      "weight": 0.04447848442941904
    },
    {
      "id": 1,
      "keywords": [
        "검색",
        "최적화",
        "엔진",
        "페이지",
        "사이트",
        "콘텐츠",
        "마케팅",
        "결과",
        "구글",
        "워드"
      ],
      "weight": 0.028638254152610898
    },
    {
      "id": 2,
      "keywords": [
        "검색",
        "엔진",
        "최적화",
        "콘텐츠",
        "페이지",
        "사이트",
        "결과",
        "마케팅",
        "구글",
        "웹사이트"
      ],
      "weight": 0.22648815717548132
    },
    {
      "id": 3,
      "keywords": [
        "검색",
        "엔진",
        "최적화",
        "사이트",
        "콘텐츠",
        "구글",
        "결과",
        "마케팅",
        "워드",
        "페이지"
      ],
      "weight": 0.015028013149276376
    },
    {
      "id": 4,
      "keywords": [
        "검색",
        "엔진",
        "최적화",
        "페이지",
        "콘텐츠",
        "사이트",
        "결과",
        "구글",
        "링크",
        "마케팅"
      ],
      "weight": 0.021933888900093734
    }
  ],
  "token_analysis": {
    "total_tokens": 16096,
    "top_tokens": [
      [
        "검색",
        988
      ],
      [
        "엔진",
        502
      ],
      [
        "최적화",
        441
      ],
      [
        "콘텐츠",
        332
      ],
      [
        "페이지",
        299
      ],
      [
        "사이트",
        261
      ],
      [
        "결과",
        192
      ],
      [
        "마케팅",
        174
      ],
      [
        "구글",
        173
      ],
      [
        "웹사이트",
        154
      ],
      [
        "링크",
        149
      ],
      [
        "워드",
        145
      ],
      [
        "노출",
        140
      ],
      [
        "네이버",
        137
      ],
      [
        "사용",
        132
      ],
      [
        "사용자",
        131
      ],
      [
        "방법",
        112
      ],
      [
        "태그",
        112
      ],
      [
        "경우",
        106
      ],
      [
        "정보",
        95
      ],
      [
        "통해",
        93
      ],
      [
        "고객",
        89
      ],
      [
        "확인",
        82
      ],
      [
        "비용",
        82
      ],
      [
        "때문",
        79
      ],
      [
        "제공",
        78
      ],
      [
        "이미지",
        77
      ],
      [
        "설정",
        74
      ],
      [
        "해당",
        72
      ],
      [
        "광고",
        72
      ],
      [
        "제목",
        68
      ],
      [
        "가장",
        67
      ],
      [
        "트래픽",
        67
      ],
      [
        "작성",
        65
      ],
      [
        "블로그",
        63
      ],
      [
        "순위",
        62
      ],
      [
        "홈페이지",
        62
      ],
      [
        "작업",
        61
      ],
      [
        "대한",
        61
      ],
      [
        "상위",
        61
      ],
      [
        "설명",
        58
      ],
      [
        "전략",
        54
      ],
      [
        "다른",
        53
      ],
      [
        "가지",
        53
      ],
      [
        "내용",
        52
      ],
      [
        "웹페이지",
        52
      ],
      [
        "포함",
        52
      ],
      [
        "위해",
        50
      ],
      [
        "텍스트",
        50
      ],
      [
        "제작",
        50
      ]
    ]
  },
  "content_guides": [
    {
      "topic_id": 0,
      "topic_weight": 0.04447848442941904,
      "main_keywords": [
        "검색",
        "엔진",
        "최적화",
        "콘텐츠",
        "사이트"
      ],
      "title_suggestions": [
        "검색엔진최적화 - 검색 및 엔진에 대한 가이드",
        "검색를 활용한 검색엔진최적화 최적화 방법",
        "검색엔진최적화에서 검색의 중요성",
        "검색와 엔진로 알아보는 검색엔진최적화"
      ],
      "heading_structure": [
        "검색와 검색엔진최적화의 관계",
        "엔진을 통한 검색엔진최적화 이해하기",
        "검색엔진최적화의 중요한 요소: 최적화와 콘텐츠",
        "검색을 활용한 검색엔진최적화 전략",
        "결론: 검색엔진최적화와 사이트의 미래"
      ],
      "content_outline": [
        "소개: 검색엔진최적화와 검색의 개요 및 중요성",
        "주요 섹션 1: 검색와 엔진의 상세 설명",
        "주요 섹션 2: 최적화의 역할과 활용 방법",
        "주요 섹션 3: 콘텐츠을 통한 효과적인 검색엔진최적화 전략",
        "사례 연구: 사이트를 활용한 성공 사례",
        "FAQ 및 자주 묻는 질문",
        "결론 및 요약"
      ]
    },
    {
      "topic_id": 1,
      "topic_weight": 0.028638254152610898,
      "main_keywords": [
        "검색",
        "최적화",
        "엔진",
        "페이지",
        "사이트"
      ],
      "title_suggestions": [
        "검색엔진최적화 - 검색 및 최적화에 대한 가이드",
        "검색를 활용한 검색엔진최적화 최적화 방법",
        "검색엔진최적화에서 검색의 중요성",
        "검색와 최적화로 알아보는 검색엔진최적화"
      ],
      "heading_structure": [
        "검색와 검색엔진최적화의 관계",
        "최적화을 통한 검색엔진최적화 이해하기",
        "검색엔진최적화의 중요한 요소: 엔진와 페이지",
        "검색을 활용한 검색엔진최적화 전략",
        "결론: 검색엔진최적화와 사이트의 미래"
      ],
      "content_outline": [
        "소개: 검색엔진최적화와 검색의 개요 및 중요성",
        "주요 섹션 1: 검색와 최적화의 상세 설명",
        "주요 섹션 2: 엔진의 역할과 활용 방법",
        "주요 섹션 3: 페이지을 통한 효과적인 검색엔진최적화 전략",
        "사례 연구: 사이트를 활용한 성공 사례",
        "FAQ 및 자주 묻는 질문",
        "결론 및 요약"
      ]
    },
    {
      "topic_id": 2,
      "topic_weight": 0.22648815717548132,
      "main_keywords": [
        "검색",
        "엔진",
        "최적화",
        "콘텐츠",
        "페이지"
      ],
      "title_suggestions": [
        "검색엔진최적화 - 검색 및 엔진에 대한 가이드",
        "검색를 활용한 검색엔진최적화 최적화 방법",
        "검색엔진최적화에서 검색의 중요성",
        "검색와 엔진로 알아보는 검색엔진최적화"
      ],
      "heading_structure": [
        "검색와 검색엔진최적화의 관계",
        "엔진을 통한 검색엔진최적화 이해하기",
        "검색엔진최적화의 중요한 요소: 최적화와 콘텐츠",
        "검색을 활용한 검색엔진최적화 전략",
        "결론: 검색엔진최적화와 페이지의 미래"
      ],
      "content_outline": [
        "소개: 검색엔진최적화와 검색의 개요 및 중요성",
        "주요 섹션 1: 검색와 엔진의 상세 설명",
        "주요 섹션 2: 최적화의 역할과 활용 방법",
        "주요 섹션 3: 콘텐츠을 통한 효과적인 검색엔진최적화 전략",
        "사례 연구: 페이지를 활용한 성공 사례",
        "FAQ 및 자주 묻는 질문",
        "결론 및 요약"
      ]
    },
    {
      "topic_id": 3,
      "topic_weight": 0.015028013149276376,
      "main_keywords": [
        "검색",
        "엔진",
        "최적화",
        "사이트",
        "콘텐츠"
      ],
      "title_suggestions": [
        "검색엔진최적화 - 검색 및 엔진에 대한 가이드",
        "검색를 활용한 검색엔진최적화 최적화 방법",
        "검색엔진최적화에서 검색의 중요성",
        "검색와 엔진로 알아보는 검색엔진최적화"
      ],
      "heading_structure": [
        "검색와 검색엔진최적화의 관계",
        "엔진을 통한 검색엔진최적화 이해하기",
        "검색엔진최적화의 중요한 요소: 최적화와 사이트",
        "검색을 활용한 검색엔진최적화 전략",
        "결론: 검색엔진최적화와 콘텐츠의 미래"
      ],
      "content_outline": [
        "소개: 검색엔진최적화와 검색의 개요 및 중요성",
        "주요 섹션 1: 검색와 엔진의 상세 설명",
        "주요 섹션 2: 최적화의 역할과 활용 방법",
        "주요 섹션 3: 사이트을 통한 효과적인 검색엔진최적화 전략",
        "사례 연구: 콘텐츠를 활용한 성공 사례",
        "FAQ 및 자주 묻는 질문",
        "결론 및 요약"
      ]
    },
    {
      "topic_id": 4,
      "topic_weight": 0.021933888900093734,
      "main_keywords": [
        "검색",
        "엔진",
        "최적화",
        "페이지",
        "콘텐츠"
      ],
      "title_suggestions": [
        "검색엔진최적화 - 검색 및 엔진에 대한 가이드",
        "검색를 활용한 검색엔진최적화 최적화 방법",
        "검색엔진최적화에서 검색의 중요성",
        "검색와 엔진로 알아보는 검색엔진최적화"
      ],
      "heading_structure": [
        "검색와 검색엔진최적화의 관계",
        "엔진을 통한 검색엔진최적화 이해하기",
        "검색엔진최적화의 중요한 요소: 최적화와 페이지",
        "검색을 활용한 검색엔진최적화 전략",
        "결론: 검색엔진최적화와 콘텐츠의 미래"
      ],
      "content_outline": [
        "소개: 검색엔진최적화와 검색의 개요 및 중요성",
        "주요 섹션 1: 검색와 엔진의 상세 설명",
        "주요 섹션 2: 최적화의 역할과 활용 방법",
        "주요 섹션 3: 페이지을 통한 효과적인 검색엔진최적화 전략",
        "사례 연구: 콘텐츠를 활용한 성공 사례",
        "FAQ 및 자주 묻는 질문",
        "결론 및 요약"
      ]
    }
  ],
  "seo_keywords": {
    "primary": [
      [
        "검색",
        988
      ],
      [
        "엔진",
        502
      ],
      [
        "최적화",
        441
      ],
      [
        "콘텐츠",
        332
      ],
      [
        "페이지",
        299
      ]
    ],
    "secondary": [
      [
        "사이트",
        261
      ],
      [
        "결과",
        192
      ],
      [
        "마케팅",
        174
      ],
      [
        "구글",
        173
      ],
      [
        "웹사이트",
        154
      ],
      [
        "링크",
        149
      ],
      [
        "워드",
        145
      ],
      [
        "노출",
        140
      ],
      [
        "네이버",
        137
      ],
      [
        "사용",
        132
      ]
    ],
    "related": [
      [
        "사용자",
        131
      ],
      [
        "방법",
        112
      ],
      [
        "태그",
        112
      ],
      [
        "경우",
        106
      ],
      [
        "정보",
        95
      ],
      [
        "통해",
        93
      ],
      [
        "고객",
        89
      ],
      [
        "확인",
        82
      ],
      [
        "비용",
        82
      ],
      [
        "때문",
        79
      ],
      [
        "제공",
        78
      ],
      [
        "이미지",
        77
      ],
      [
        "설정",
        74
      ],
      [
        "해당",
        72
      ],
      [
        "광고",
        72
      ]
    ]
  },
  "timestamp": "20250323_160928",
  "saved_files": {
    "search_results": "검색엔진최적화_20250323_160928_search_results.json",
    "extracted_content": "검색엔진최적화_20250323_160928_extracted_content.json",
    "analysis_result": "검색엔진최적화_20250323_160928_lda_analysis.json"
  }
}